odoo/addons/account_multi_vat/README.rst
odoo/addons/account_multi_vat/__init__.py
odoo/addons/account_multi_vat/__manifest__.py
odoo/addons/account_multi_vat/data/res_partner_id_category.xml
odoo/addons/account_multi_vat/i18n/account_multi_vat.pot
odoo/addons/account_multi_vat/i18n/fr.po
odoo/addons/account_multi_vat/models/__init__.py
odoo/addons/account_multi_vat/models/account_fiscal_position.py
odoo/addons/account_multi_vat/models/account_move.py
odoo/addons/account_multi_vat/models/account_tax.py
odoo/addons/account_multi_vat/models/account_tax_repartition_line.py
odoo/addons/account_multi_vat/models/res_partner.py
odoo/addons/account_multi_vat/models/res_partner_id_category.py
odoo/addons/account_multi_vat/models/res_partner_id_number.py
odoo/addons/account_multi_vat/readme/CONFIGURATION.rst
odoo/addons/account_multi_vat/readme/CONTRIBUTORS.rst
odoo/addons/account_multi_vat/readme/DESCRIPTION.rst
odoo/addons/account_multi_vat/readme/USAGE.rst
odoo/addons/account_multi_vat/static/description/icon.png
odoo/addons/account_multi_vat/static/description/index.html
odoo/addons/account_multi_vat/tests/__init__.py
odoo/addons/account_multi_vat/tests/common.py
odoo/addons/account_multi_vat/tests/test_account_multi_vat.py
odoo/addons/account_multi_vat/views/account_fiscal_position.xml
odoo/addons/account_multi_vat/views/account_move.xml
odoo/addons/account_multi_vat/views/account_tax.xml
odoo/addons/account_multi_vat/views/report_invoice.xml
odoo/addons/account_multi_vat/views/res_partner.xml
odoo/addons/account_multi_vat/wizards/__init__.py
odoo/addons/account_multi_vat/wizards/account_move_reversal.py
odoo13_addon_account_multi_vat-13.0.1.0.1.dev5.dist-info/METADATA
odoo13_addon_account_multi_vat-13.0.1.0.1.dev5.dist-info/WHEEL
odoo13_addon_account_multi_vat-13.0.1.0.1.dev5.dist-info/top_level.txt
odoo13_addon_account_multi_vat-13.0.1.0.1.dev5.dist-info/RECORD
